setup.py
teamcitynosetests/__init__.py
teamcitynosetests.egg-info/PKG-INFO
teamcitynosetests.egg-info/SOURCES.txt
teamcitynosetests.egg-info/dependency_links.txt
teamcitynosetests.egg-info/entry_points.txt
teamcitynosetests.egg-info/requires.txt
teamcitynosetests.egg-info/top_level.txt