Metadata-Version: 1.0
Name: teamcitynosetests
Version: 0.2dev
Summary: Team City nosetests plugin to generate service messages
Home-page: https://github.com/Intelliflo/teamcity-nosetests
Author: Chris Smith
Author-email: chris.smith@intelliflo.com
License: Apache License, Version 2.0
Platform: UNKNOWN
